{
  "activity_id": "2026-02-16T14:08:00-CME-001",
  "launch_time": "2026-02-16T14:08:00.0000000Z",
  "initial_speed_kms": 455,
  "observed_transit_hours": 104.45,
  "arrival_time_hours": null,
  "error_hours": null,
  "termination_reason": "timeout",
  "shock_arrived": false,
  "n_missing_hours": 2,
  "density_coverage": 0.9861111111111112,
  "gamma_eff_mean": 7.3623910336239114E-09,
  "gamma_eff_final": 2E-08,
  "trajectory": [
    {
      "hour_index": 0,
      "time_hours": 0,
      "r_solar_radii": 21.5,
      "speed_km_s": 455,
      "gamma_km_inv": 5.272727272727272E-09,
      "n_obs": 2.9,
      "v_obs": 637,
      "gamma_fellback": false
    },
    {
      "hour_index": 1,
      "time_hours": 1,
      "r_solar_radii": 23.854309554290786,
      "speed_km_s": 454.9406640827906,
      "gamma_km_inv": 5.454545454545454E-09,
      "n_obs": 3,
      "v_obs": 644,
      "gamma_fellback": false
    },
    {
      "hour_index": 2,
      "time_hours": 2,
      "r_solar_radii": 26.20826136455046,
      "speed_km_s": 454.861748394047,
      "gamma_km_inv": 7.272727272727273E-09,
      "n_obs": 4,
      "v_obs": 653,
      "gamma_fellback": false
    },
    {
      "hour_index": 3,
      "time_hours": 3,
      "r_solar_radii": 28.561790139142445,
      "speed_km_s": 454.777166486732,
      "gamma_km_inv": 7.818181818181818E-09,
      "n_obs": 4.3,
      "v_obs": 658,
      "gamma_fellback": false
    },
    {
      "hour_index": 4,
      "time_hours": 4,
      "r_solar_radii": 30.91486669468031,
      "speed_km_s": 454.6869717735681,
      "gamma_km_inv": 8.363636363636364E-09,
      "n_obs": 4.6,
      "v_obs": 669,
      "gamma_fellback": false
    },
    {
      "hour_index": 5,
      "time_hours": 5,
      "r_solar_radii": 33.26744697495517,
      "speed_km_s": 454.5853695330271,
      "gamma_km_inv": 9.454545454545454E-09,
      "n_obs": 5.2,
      "v_obs": 659,
      "gamma_fellback": false
    },
    {
      "hour_index": 6,
      "time_hours": 6,
      "r_solar_radii": 35.61955785838062,
      "speed_km_s": 454.5055258693136,
      "gamma_km_inv": 7.454545454545455E-09,
      "n_obs": 4.1,
      "v_obs": 672,
      "gamma_fellback": false
    },
    {
      "hour_index": 7,
      "time_hours": 7,
      "r_solar_radii": 37.971276270669435,
      "speed_km_s": 454.4336720757242,
      "gamma_km_inv": 6.727272727272728E-09,
      "n_obs": 3.7,
      "v_obs": 659,
      "gamma_fellback": false
    },
    {
      "hour_index": 8,
      "time_hours": 8,
      "r_solar_radii": 40.32264840362068,
      "speed_km_s": 454.37168085602775,
      "gamma_km_inv": 5.818181818181819E-09,
      "n_obs": 3.2,
      "v_obs": 658,
      "gamma_fellback": false
    },
    {
      "hour_index": 9,
      "time_hours": 9,
      "r_solar_radii": 42.67368512346366,
      "speed_km_s": 454.3040394306567,
      "gamma_km_inv": 6.363636363636363E-09,
      "n_obs": 3.5,
      "v_obs": 647,
      "gamma_fellback": false
    },
    {
      "hour_index": 10,
      "time_hours": 10,
      "r_solar_radii": 45.024367272489414,
      "speed_km_s": 454.2346407497397,
      "gamma_km_inv": 6.545454545454546E-09,
      "n_obs": 3.6,
      "v_obs": 637,
      "gamma_fellback": false
    },
    {
      "hour_index": 11,
      "time_hours": 11,
      "r_solar_radii": 47.3747156337986,
      "speed_km_s": 454.17502275350955,
      "gamma_km_inv": 5.6363636363636365E-09,
      "n_obs": 3.1,
      "v_obs": 654,
      "gamma_fellback": false
    },
    {
      "hour_index": 12,
      "time_hours": 12,
      "r_solar_radii": 49.72478065051381,
      "speed_km_s": 454.1251215355002,
      "gamma_km_inv": 4.727272727272727E-09,
      "n_obs": 2.6,
      "v_obs": 677,
      "gamma_fellback": false
    },
    {
      "hour_index": 13,
      "time_hours": 13,
      "r_solar_radii": 52.0745827289077,
      "speed_km_s": 454.0733982476287,
      "gamma_km_inv": 4.90909090909091E-09,
      "n_obs": 2.7,
      "v_obs": 648,
      "gamma_fellback": false
    },
    {
      "hour_index": 14,
      "time_hours": 14,
      "r_solar_radii": 54.42413225069329,
      "speed_km_s": 454.0275049115914,
      "gamma_km_inv": 4.363636363636364E-09,
      "n_obs": 2.4,
      "v_obs": 642,
      "gamma_fellback": false
    },
    {
      "hour_index": 15,
      "time_hours": 15,
      "r_solar_radii": 56.7734543682225,
      "speed_km_s": 453.98550440129105,
      "gamma_km_inv": 4E-09,
      "n_obs": 2.2,
      "v_obs": 645,
      "gamma_fellback": false
    },
    {
      "hour_index": 16,
      "time_hours": 16,
      "r_solar_radii": 59.122574109613765,
      "speed_km_s": 453.9492837496911,
      "gamma_km_inv": 3.4545454545454547E-09,
      "n_obs": 1.9,
      "v_obs": 620,
      "gamma_fellback": false
    },
    {
      "hour_index": 17,
      "time_hours": 17,
      "r_solar_radii": 61.47150162321831,
      "speed_km_s": 453.9112092186208,
      "gamma_km_inv": 3.6363636363636364E-09,
      "n_obs": 2,
      "v_obs": 615,
      "gamma_fellback": false
    },
    {
      "hour_index": 18,
      "time_hours": 18,
      "r_solar_radii": 63.82022241923165,
      "speed_km_s": 453.869389258248,
      "gamma_km_inv": 4E-09,
      "n_obs": 2.2,
      "v_obs": 599,
      "gamma_fellback": false
    },
    {
      "hour_index": 19,
      "time_hours": 19,
      "r_solar_radii": 66.16870734401294,
      "speed_km_s": 453.8200492404524,
      "gamma_km_inv": 4.727272727272727E-09,
      "n_obs": 2.6,
      "v_obs": 585,
      "gamma_fellback": false
    },
    {
      "hour_index": 20,
      "time_hours": 20,
      "r_solar_radii": 68.51693718549802,
      "speed_km_s": 453.77079952290643,
      "gamma_km_inv": 4.727272727272727E-09,
      "n_obs": 2.6,
      "v_obs": 572,
      "gamma_fellback": false
    },
    {
      "hour_index": 21,
      "time_hours": 21,
      "r_solar_radii": 70.86492219178442,
      "speed_km_s": 453.72541817911866,
      "gamma_km_inv": 4.363636363636364E-09,
      "n_obs": 2.4,
      "v_obs": 566,
      "gamma_fellback": false
    },
    {
      "hour_index": 22,
      "time_hours": 22,
      "r_solar_radii": 73.21267256387104,
      "speed_km_s": 453.6801133723995,
      "gamma_km_inv": 4.363636363636364E-09,
      "n_obs": 2.4,
      "v_obs": 560,
      "gamma_fellback": false
    },
    {
      "hour_index": 23,
      "time_hours": 23,
      "r_solar_radii": 75.56018382293476,
      "speed_km_s": 453.63300204390504,
      "gamma_km_inv": 4.545454545454545E-09,
      "n_obs": 2.5,
      "v_obs": 582,
      "gamma_fellback": false
    },
    {
      "hour_index": 24,
      "time_hours": 24,
      "r_solar_radii": 77.9074515114926,
      "speed_km_s": 453.58597333561977,
      "gamma_km_inv": 4.545454545454545E-09,
      "n_obs": 2.5,
      "v_obs": 567,
      "gamma_fellback": false
    },
    {
      "hour_index": 25,
      "time_hours": 25,
      "r_solar_radii": 80.25445177340394,
      "speed_km_s": 453.52964763866134,
      "gamma_km_inv": 5.454545454545454E-09,
      "n_obs": 3,
      "v_obs": 566,
      "gamma_fellback": false
    },
    {
      "hour_index": 26,
      "time_hours": 26,
      "r_solar_radii": 82.60116087607831,
      "speed_km_s": 453.4734402283608,
      "gamma_km_inv": 5.454545454545454E-09,
      "n_obs": 3,
      "v_obs": 571,
      "gamma_fellback": false
    },
    {
      "hour_index": 27,
      "time_hours": 27,
      "r_solar_radii": 84.94759393874061,
      "speed_km_s": 453.42295438651024,
      "gamma_km_inv": 4.90909090909091E-09,
      "n_obs": 2.7,
      "v_obs": 571,
      "gamma_fellback": false
    },
    {
      "hour_index": 28,
      "time_hours": 28,
      "r_solar_radii": 87.2937563476189,
      "speed_km_s": 453.3688349292233,
      "gamma_km_inv": 5.272727272727272E-09,
      "n_obs": 2.9,
      "v_obs": 564,
      "gamma_fellback": false
    },
    {
      "hour_index": 29,
      "time_hours": 29,
      "r_solar_radii": 89.6396389911156,
      "speed_km_s": 453.3148250110508,
      "gamma_km_inv": 5.272727272727272E-09,
      "n_obs": 2.9,
      "v_obs": 574,
      "gamma_fellback": false
    },
    {
      "hour_index": 30,
      "time_hours": 30,
      "r_solar_radii": 91.98519917861273,
      "speed_km_s": 453.2442186459319,
      "gamma_km_inv": 6.909090909090909E-09,
      "n_obs": 3.8,
      "v_obs": 549,
      "gamma_fellback": false
    },
    {
      "hour_index": 31,
      "time_hours": 31,
      "r_solar_radii": 94.3304040724226,
      "speed_km_s": 453.177500696142,
      "gamma_km_inv": 6.545454545454546E-09,
      "n_obs": 3.6,
      "v_obs": 538,
      "gamma_fellback": false
    },
    {
      "hour_index": 32,
      "time_hours": 32,
      "r_solar_radii": 96.67528328278553,
      "speed_km_s": 453.118336063294,
      "gamma_km_inv": 5.818181818181819E-09,
      "n_obs": 3.2,
      "v_obs": 532,
      "gamma_fellback": false
    },
    {
      "hour_index": 33,
      "time_hours": 33,
      "r_solar_radii": 99.01986622066863,
      "speed_km_s": 453.06298866188666,
      "gamma_km_inv": 5.454545454545454E-09,
      "n_obs": 3,
      "v_obs": 542,
      "gamma_fellback": false
    },
    {
      "hour_index": 34,
      "time_hours": 34,
      "r_solar_radii": 101.36415353055756,
      "speed_km_s": 453.0040784229072,
      "gamma_km_inv": 5.818181818181819E-09,
      "n_obs": 3.2,
      "v_obs": 540,
      "gamma_fellback": false
    },
    {
      "hour_index": 35,
      "time_hours": 35,
      "r_solar_radii": 103.70812208776202,
      "speed_km_s": 452.9397949401108,
      "gamma_km_inv": 6.363636363636363E-09,
      "n_obs": 3.5,
      "v_obs": 546,
      "gamma_fellback": false
    },
    {
      "hour_index": 36,
      "time_hours": 36,
      "r_solar_radii": 106.05173471357591,
      "speed_km_s": 452.86651876857553,
      "gamma_km_inv": 7.272727272727273E-09,
      "n_obs": 4,
      "v_obs": 538,
      "gamma_fellback": false
    },
    {
      "hour_index": 37,
      "time_hours": 37,
      "r_solar_radii": 108.39499231068797,
      "speed_km_s": 452.8025683169231,
      "gamma_km_inv": 6.363636363636363E-09,
      "n_obs": 3.5,
      "v_obs": 541,
      "gamma_fellback": false
    },
    {
      "hour_index": 38,
      "time_hours": 38,
      "r_solar_radii": 110.73792410124825,
      "speed_km_s": 452.74059299604943,
      "gamma_km_inv": 6.181818181818182E-09,
      "n_obs": 3.4,
      "v_obs": 544,
      "gamma_fellback": false
    },
    {
      "hour_index": 39,
      "time_hours": 39,
      "r_solar_radii": 113.08053556776213,
      "speed_km_s": 452.6787629877098,
      "gamma_km_inv": 6.181818181818182E-09,
      "n_obs": 3.4,
      "v_obs": 539,
      "gamma_fellback": false
    },
    {
      "hour_index": 40,
      "time_hours": 40,
      "r_solar_radii": 115.42280869349378,
      "speed_km_s": 452.60983019459917,
      "gamma_km_inv": 6.909090909090909E-09,
      "n_obs": 3.8,
      "v_obs": 536,
      "gamma_fellback": false
    },
    {
      "hour_index": 41,
      "time_hours": 41,
      "r_solar_radii": 117.76471154652239,
      "speed_km_s": 452.535657383457,
      "gamma_km_inv": 7.454545454545455E-09,
      "n_obs": 4.1,
      "v_obs": 525,
      "gamma_fellback": false
    },
    {
      "hour_index": 42,
      "time_hours": 42,
      "r_solar_radii": 120.10626845190502,
      "speed_km_s": 452.47610905871244,
      "gamma_km_inv": 6E-09,
      "n_obs": 3.3,
      "v_obs": 521,
      "gamma_fellback": false
    },
    {
      "hour_index": 43,
      "time_hours": 43,
      "r_solar_radii": 122.44750359649213,
      "speed_km_s": 452.41130102001944,
      "gamma_km_inv": 6.545454545454546E-09,
      "n_obs": 3.6,
      "v_obs": 515,
      "gamma_fellback": false
    },
    {
      "hour_index": 44,
      "time_hours": 44,
      "r_solar_radii": 124.78838057732193,
      "speed_km_s": 452.337686560063,
      "gamma_km_inv": 7.454545454545455E-09,
      "n_obs": 4.1,
      "v_obs": 517,
      "gamma_fellback": false
    },
    {
      "hour_index": 45,
      "time_hours": 45,
      "r_solar_radii": 127.12888179454782,
      "speed_km_s": 452.2660665888697,
      "gamma_km_inv": 7.272727272727273E-09,
      "n_obs": 4,
      "v_obs": 525,
      "gamma_fellback": false
    },
    {
      "hour_index": 46,
      "time_hours": 46,
      "r_solar_radii": 129.46901291070301,
      "speed_km_s": 452.19464236231084,
      "gamma_km_inv": 7.272727272727273E-09,
      "n_obs": 4,
      "v_obs": 514,
      "gamma_fellback": false
    },
    {
      "hour_index": 47,
      "time_hours": 47,
      "r_solar_radii": 131.8087611218731,
      "speed_km_s": 452.11807871914647,
      "gamma_km_inv": 7.818181818181818E-09,
      "n_obs": 4.3,
      "v_obs": 498,
      "gamma_fellback": false
    },
    {
      "hour_index": 48,
      "time_hours": 48,
      "r_solar_radii": 134.1481045423527,
      "speed_km_s": 452.0381941422028,
      "gamma_km_inv": 8.181818181818183E-09,
      "n_obs": 4.5,
      "v_obs": 496,
      "gamma_fellback": false
    },
    {
      "hour_index": 49,
      "time_hours": 49,
      "r_solar_radii": 136.48704437540283,
      "speed_km_s": 451.9620884602598,
      "gamma_km_inv": 7.818181818181818E-09,
      "n_obs": 4.3,
      "v_obs": 506,
      "gamma_fellback": false
    },
    {
      "hour_index": 50,
      "time_hours": 50,
      "r_solar_radii": 138.82528565928726,
      "speed_km_s": 451.7684088461861,
      "gamma_km_inv": 2E-08,
      "n_obs": null,
      "v_obs": null,
      "gamma_fellback": true
    },
    {
      "hour_index": 51,
      "time_hours": 51,
      "r_solar_radii": 141.16283148583173,
      "speed_km_s": 451.69308966777356,
      "gamma_km_inv": 7.818181818181818E-09,
      "n_obs": 4.3,
      "v_obs": 475,
      "gamma_fellback": false
    },
    {
      "hour_index": 52,
      "time_hours": 52,
      "r_solar_radii": 143.49997006422393,
      "speed_km_s": 451.61101435349264,
      "gamma_km_inv": 8.545454545454546E-09,
      "n_obs": 4.7,
      "v_obs": 475,
      "gamma_fellback": false
    },
    {
      "hour_index": 53,
      "time_hours": 53,
      "r_solar_radii": 145.83665310038347,
      "speed_km_s": 451.51703621554014,
      "gamma_km_inv": 9.81818181818182E-09,
      "n_obs": 5.4,
      "v_obs": 459,
      "gamma_fellback": false
    },
    {
      "hour_index": 54,
      "time_hours": 54,
      "r_solar_radii": 148.17290005091837,
      "speed_km_s": 451.4424461912016,
      "gamma_km_inv": 7.818181818181818E-09,
      "n_obs": 4.3,
      "v_obs": 469,
      "gamma_fellback": false
    },
    {
      "hour_index": 55,
      "time_hours": 55,
      "r_solar_radii": 150.5087258057346,
      "speed_km_s": 451.3542584818564,
      "gamma_km_inv": 9.272727272727273E-09,
      "n_obs": 5.1,
      "v_obs": 461,
      "gamma_fellback": false
    },
    {
      "hour_index": 56,
      "time_hours": 56,
      "r_solar_radii": 152.8440648146043,
      "speed_km_s": 451.25433332090836,
      "gamma_km_inv": 1.0545454545454545E-08,
      "n_obs": 5.8,
      "v_obs": 458,
      "gamma_fellback": false
    },
    {
      "hour_index": 57,
      "time_hours": 57,
      "r_solar_radii": 155.17892325677857,
      "speed_km_s": 451.16850253051535,
      "gamma_km_inv": 9.09090909090909E-09,
      "n_obs": 5,
      "v_obs": 462,
      "gamma_fellback": false
    },
    {
      "hour_index": 58,
      "time_hours": 58,
      "r_solar_radii": 157.51332060339436,
      "speed_km_s": 451.0761275751658,
      "gamma_km_inv": 9.81818181818182E-09,
      "n_obs": 5.4,
      "v_obs": 464,
      "gamma_fellback": false
    },
    {
      "hour_index": 59,
      "time_hours": 59,
      "r_solar_radii": 159.8472187701422,
      "speed_km_s": 450.97557991673403,
      "gamma_km_inv": 1.0727272727272727E-08,
      "n_obs": 5.9,
      "v_obs": 472,
      "gamma_fellback": false
    },
    {
      "hour_index": 60,
      "time_hours": 60,
      "r_solar_radii": 162.180610829959,
      "speed_km_s": 450.88051035927225,
      "gamma_km_inv": 1.0181818181818181E-08,
      "n_obs": 5.6,
      "v_obs": 478,
      "gamma_fellback": false
    },
    {
      "hour_index": 61,
      "time_hours": 61,
      "r_solar_radii": 164.51352060236064,
      "speed_km_s": 450.78917137928653,
      "gamma_km_inv": 9.81818181818182E-09,
      "n_obs": 5.4,
      "v_obs": 470,
      "gamma_fellback": false
    },
    {
      "hour_index": 62,
      "time_hours": 62,
      "r_solar_radii": 166.84594550242102,
      "speed_km_s": 450.69311311016116,
      "gamma_km_inv": 1.0363636363636364E-08,
      "n_obs": 5.7,
      "v_obs": 456,
      "gamma_fellback": false
    },
    {
      "hour_index": 63,
      "time_hours": 63,
      "r_solar_radii": 169.17784823153266,
      "speed_km_s": 450.5873652996432,
      "gamma_km_inv": 1.1454545454545456E-08,
      "n_obs": 6.3,
      "v_obs": 464,
      "gamma_fellback": false
    },
    {
      "hour_index": 64,
      "time_hours": 64,
      "r_solar_radii": 171.50922650518226,
      "speed_km_s": 450.4903994800411,
      "gamma_km_inv": 1.0545454545454545E-08,
      "n_obs": 5.8,
      "v_obs": 465,
      "gamma_fellback": false
    },
    {
      "hour_index": 65,
      "time_hours": 65,
      "r_solar_radii": 173.8401125889451,
      "speed_km_s": 450.397129379511,
      "gamma_km_inv": 1.0181818181818181E-08,
      "n_obs": 5.6,
      "v_obs": 466,
      "gamma_fellback": false
    },
    {
      "hour_index": 66,
      "time_hours": 66,
      "r_solar_radii": 176.17054696373052,
      "speed_km_s": 450.3158002590811,
      "gamma_km_inv": 8.90909090909091E-09,
      "n_obs": 4.9,
      "v_obs": 464,
      "gamma_fellback": false
    },
    {
      "hour_index": 67,
      "time_hours": 67,
      "r_solar_radii": 178.50058256140895,
      "speed_km_s": 450.2429933861955,
      "gamma_km_inv": 8E-09,
      "n_obs": 4.4,
      "v_obs": 473,
      "gamma_fellback": false
    },
    {
      "hour_index": 68,
      "time_hours": 68,
      "r_solar_radii": 180.8302291545747,
      "speed_km_s": 450.16545479089257,
      "gamma_km_inv": 8.545454545454546E-09,
      "n_obs": 4.7,
      "v_obs": 478,
      "gamma_fellback": false
    },
    {
      "hour_index": 69,
      "time_hours": 69,
      "r_solar_radii": 183.15944961650695,
      "speed_km_s": 450.0783042575668,
      "gamma_km_inv": 9.636363636363637E-09,
      "n_obs": 5.3,
      "v_obs": 479,
      "gamma_fellback": false
    },
    {
      "hour_index": 70,
      "time_hours": 70,
      "r_solar_radii": 185.48824955351202,
      "speed_km_s": 450.00290926017556,
      "gamma_km_inv": 8.363636363636364E-09,
      "n_obs": 4.6,
      "v_obs": 482,
      "gamma_fellback": false
    },
    {
      "hour_index": 71,
      "time_hours": 71,
      "r_solar_radii": 187.81668106649946,
      "speed_km_s": 449.9359004623161,
      "gamma_km_inv": 7.454545454545455E-09,
      "n_obs": 4.1,
      "v_obs": 502,
      "gamma_fellback": false
    },
    {
      "hour_index": 72,
      "time_hours": 72,
      "r_solar_radii": 190.14447586942063,
      "speed_km_s": 449.757004881615,
      "gamma_km_inv": 2E-08,
      "n_obs": null,
      "v_obs": null,
      "gamma_fellback": true
    }
  ]
}